pltplus/__init__.py
pltplus-1.0.dist-info/METADATA
pltplus-1.0.dist-info/WHEEL
pltplus-1.0.dist-info/top_level.txt
pltplus-1.0.dist-info/RECORD
