Metadata-Version: 2.1
Name: pltplus
Version: 1.0
Summary: s
Home-page: https://github.com/alexhagen/pltplus
Author: Alex Hagen
Author-email: alexhagen6@gmail.com
License: UNKNOWN
Platform: UNKNOWN
Requires: matplotlib
